LICENSE.rst
README.rst
__version__.py
setup.cfg
setup.py
make_colors_tc/__init__.py
make_colors_tc/__version__.py
make_colors_tc/make_colors_tc.py
make_colors_tc.egg-info/PKG-INFO
make_colors_tc.egg-info/SOURCES.txt
make_colors_tc.egg-info/dependency_links.txt
make_colors_tc.egg-info/top_level.txt